README.md
setup.py
src/hookrun.py
src/hook_run.egg-info/PKG-INFO
src/hook_run.egg-info/SOURCES.txt
src/hook_run.egg-info/dependency_links.txt
src/hook_run.egg-info/entry_points.txt
src/hook_run.egg-info/top_level.txt