Metadata-Version: 2.1
Name: hook-run
Version: 1.0.0
Summary: Run commands using Python virtual environment
Home-page: https://github.com/Kirusi/hook-run
Author: Kirusi Msafiri
Author-email: kirusi.msafiri@gmail.com
License: UNKNOWN
Platform: UNKNOWN
Classifier: Development Status :: 5 - Production/Stable
Classifier: Environment :: Console
Classifier: Intended Audience :: Developers
Classifier: Intended Audience :: System Administrators
Classifier: License :: OSI Approved :: MIT License
Classifier: Topic :: Software Development
Classifier: Topic :: Utilities
Requires-Python: ~=3.7
